setup.py
thumbot.py
thumbot.egg-info/PKG-INFO
thumbot.egg-info/SOURCES.txt
thumbot.egg-info/dependency_links.txt
thumbot.egg-info/requires.txt
thumbot.egg-info/top_level.txt