Metadata-Version: 1.0
Name: thumbot
Version: 0.1.0
Summary: A :thumbsup: and :thumbsdown: counter keyboard for Telegram bots and channels
Home-page: https://github.com/rougeth/thumbot
Author: Marco Rougeth
Author-email: marco@rougeth.com
License: MIT
Keywords: telegram bots channels
Platform: UNKNOWN
